cellworld2/__init__.py
cellworld2-0.0.167.dist-info/METADATA
cellworld2-0.0.167.dist-info/WHEEL
cellworld2-0.0.167.dist-info/top_level.txt
cellworld2-0.0.167.dist-info/RECORD
