Metadata-Version: 2.1
Name: cellworld2
Version: 0.0.167
Summary: Maciver Lab computational biology research package
Home-page: UNKNOWN
Author: german espinosa
Author-email: germanespinosa@gmail.com
License: MIT
Platform: UNKNOWN
